dnss/__init__.py
dnss/main.py
dnss/data/__init__.py
dnss/data/loader.py
dnss/models/__init__.py
dnss/models/cross_sectional_var.py
dnss/models/kalman_filter.py
dnss/utils/__init__.py
dnss/utils/helpers.py
dnss/utils/logging.py
dns_yield_curve-0.1.0.dist-info/METADATA
dns_yield_curve-0.1.0.dist-info/WHEEL
dns_yield_curve-0.1.0.dist-info/top_level.txt
dns_yield_curve-0.1.0.dist-info/RECORD
