Metadata-Version: 2.4
Name: dns-yield-curve
Version: 0.1.0
Summary: Dynamic Nelson Siegel model for yield curve estimation and forecasting
Author-email: Sem van Embden <semvanembden@gmail.com>
Maintainer-email: Sem van Embden <semvanembden@gmail.com>
License: MIT
Project-URL: Homepage, https://github.com/svembden/dns-yield-curve
Project-URL: Bug Reports, https://github.com/svembden/dns-yield-curve/issues
Project-URL: Source, https://github.com/svembden/dns-yield-curve
Keywords: yield curve,nelson siegel,finance,time series,forecasting,kalman,dynamic nelson siegel
Classifier: Development Status :: 3 - Alpha
Classifier: Intended Audience :: Financial and Insurance Industry
Classifier: Intended Audience :: Science/Research
Classifier: Operating System :: OS Independent
Classifier: Programming Language :: Python :: 3
Classifier: Programming Language :: Python :: 3.8
Classifier: Programming Language :: Python :: 3.9
Classifier: Programming Language :: Python :: 3.10
Classifier: Programming Language :: Python :: 3.11
Classifier: Programming Language :: Python :: 3.12
Classifier: Topic :: Scientific/Engineering :: Mathematics
Classifier: Topic :: Office/Business :: Financial
Requires-Python: >=3.8
Requires-Dist: pandas>=1.0.0
Requires-Dist: numpy>=1.18.0
Requires-Dist: scipy>=1.4.0
Requires-Dist: statsmodels>=0.11.0
Requires-Dist: scikit-learn>=0.22.0
Provides-Extra: dev
Requires-Dist: pytest>=6.0; extra == "dev"
Requires-Dist: pytest-cov; extra == "dev"
Requires-Dist: black; extra == "dev"
Requires-Dist: flake8; extra == "dev"
Requires-Dist: jupyter; extra == "dev"
Requires-Dist: matplotlib>=3.0.0; extra == "dev"
Provides-Extra: examples
Requires-Dist: matplotlib>=3.0.0; extra == "examples"
Requires-Dist: jupyter; extra == "examples"
